LICENSE
MANIFEST.in
README.md
setup.py
compress_json/__init__.py
compress_json/__version__.py
compress_json/compress_json.py
compress_json/py.typed
compress_json.egg-info/PKG-INFO
compress_json.egg-info/SOURCES.txt
compress_json.egg-info/dependency_links.txt
compress_json.egg-info/requires.txt
compress_json.egg-info/top_level.txt