Metadata-Version: 2.1
Name: compress-json
Version: 1.1.1
Summary: The missing Python utility to read and write large compressed JSONs.
Home-page: https://github.com/LucaCappelletti94/compress_json
Author: Luca Cappelletti
Author-email: cappelletti.luca94@gmail.com
License: MIT
Platform: UNKNOWN
Classifier: Development Status :: 5 - Production/Stable
Classifier: License :: OSI Approved :: MIT License
Classifier: Programming Language :: Python :: 3
Provides-Extra: test
License-File: LICENSE
